django_openid_connect/__init__.py
django_openid_connect/backends.py
django_openid_connect/pipeline.py
django_openid_connect/settings.py
django_openid_connect/urls.py
django_openid_connect/wsgi.py
django_openid_connect-1.0.0.dist-info/LICENSE
django_openid_connect-1.0.0.dist-info/WHEEL
django_openid_connect-1.0.0.dist-info/METADATA
django_openid_connect-1.0.0.dist-info/RECORD
